jqfpy/__init__.py
jqfpy/__main__.py
jqfpy/_tree.py
jqfpy/accessor.py
jqfpy/cli.py
jqfpy/helpermodule.py
jqfpy/langhelpers.py
jqfpy/loading/__init__.py
jqfpy/loading/_json.py
jqfpy/loading/_ltsv.py
jqfpy/loading/_raw.py
jqfpy/loading/_yaml.py
jqfpy/loading/rec.py
jqfpy-0.6.2.dist-info/METADATA
jqfpy-0.6.2.dist-info/WHEEL
jqfpy-0.6.2.dist-info/entry_points.txt
jqfpy-0.6.2.dist-info/top_level.txt
jqfpy-0.6.2.dist-info/RECORD
