Metadata-Version: 2.1
Name: jqfpy
Version: 0.6.2
Summary: jq for pythonista
Home-page: https://github.com/podhmo/jqfpy
Author: podhmo
Author-email: ababjam61+github@gmail.com
License: UNKNOWN
Keywords: jq
Platform: UNKNOWN
Classifier: Programming Language :: Python
Classifier: Programming Language :: Python :: 3
Classifier: Programming Language :: Python :: 3.5
Classifier: Programming Language :: Python :: 3.6
Classifier: Programming Language :: Python :: Implementation :: CPython
Classifier: Programming Language :: Python :: Implementation :: PyPy
Requires-Dist: magicalimport
Provides-Extra: dev
Requires-Dist: black ; extra == 'dev'
Provides-Extra: docs
Provides-Extra: testing
Provides-Extra: yaml
Requires-Dist: PyYAML ; extra == 'yaml'
